{
  "name": "blaziken",
  "height": 19,
  "weight": 520,
  "types": [
    {
      "type": {
        "name": "fire"
      }
    },
    {
      "type": {
        "name": "fighting"
      }
    }
  ],
  "abilities": [
    {
      "ability": {
        "name": "blaze"
      }
    },
    {
      "ability": {
        "name": "speed-boost"
      }
    }
  ],
  "stats": [
    {
      "stat": {
        "name": "hp"
      },
      "base_stat": 80
    },
    {
      "stat": {
        "name": "attack"
      },
      "base_stat": 120
    },
    {
      "stat": {
        "name": "defense"
      },
      "base_stat": 70
    },
    {
      "stat": {
        "name": "special-attack"
      },
      "base_stat": 110
    },
    {
      "stat": {
        "name": "special-defense"
      },
      "base_stat": 70
    },
    {
      "stat": {
        "name": "speed"
      },
      "base_stat": 80
    }
  ]
}