{
  "name": "munna",
  "height": 6,
  "weight": 233,
  "types": [
    {
      "type": {
        "name": "psychic"
      }
    }
  ],
  "abilities": [
    {
      "ability": {
        "name": "forewarn"
      }
    },
    {
      "ability": {
        "name": "synchronize"
      }
    },
    {
      "ability": {
        "name": "telepathy"
      }
    }
  ],
  "stats": [
    {
      "stat": {
        "name": "hp"
      },
      "base_stat": 76
    },
    {
      "stat": {
        "name": "attack"
      },
      "base_stat": 25
    },
    {
      "stat": {
        "name": "defense"
      },
      "base_stat": 45
    },
    {
      "stat": {
        "name": "special-attack"
      },
      "base_stat": 67
    },
    {
      "stat": {
        "name": "special-defense"
      },
      "base_stat": 55
    },
    {
      "stat": {
        "name": "speed"
      },
      "base_stat": 24
    }
  ]
}